piXnotify/NotifierBuilder.py
piXnotify/__init__.py
piXnotify/OSNotifiers/AbstractNotifier.py
piXnotify/OSNotifiers/linux/LinuxNotifier.py
piXnotify/OSNotifiers/macosx/MacNotifier.py
piXnotify-0.0.1.dist-info/LICENSE.txt
piXnotify-0.0.1.dist-info/METADATA
piXnotify-0.0.1.dist-info/WHEEL
piXnotify-0.0.1.dist-info/top_level.txt
piXnotify-0.0.1.dist-info/RECORD
