Metadata-Version: 2.1
Name: piXnotify
Version: 0.0.1
Summary: A cross-platform notificartion library
Home-page: https://git.soma.salesforce.com/franck-barbedor/piXnotify
Author: franck.barbedor
Author-email: franck.barbedor@salesforce.com
License: UNKNOWN
Platform: UNKNOWN
Classifier: Programming Language :: Python :: 3
Classifier: License :: OSI Approved :: BSD License
Classifier: Operating System :: OS Independent
Requires-Python: >=3.6
Requires-Dist: pync ; platform_system == "Darwin"
Requires-Dist: notify2 ; platform_system == "Linux"
